{
  "id": "fsar_b71c1208-85de-43a9-b889-e6b40cb32af0",
  "timestamp": "2026-01-01T05:28:46.736Z",
  "proposal": "idea_implementation: Create or update the file config.json with this complete content:\n\n{\n  \"database_name\": \"workflows\",\n  \"host\": \"your-db-connection-string-here\" // Replace with your actual database connection string or config file path if needed\n}\n\nThis is for opportunity: Make.com Automation Scenarios\nMake sure the file is complete, working, and production-ready.",
  "severity": 6,
  "risks": [
    "Slow failure: unnoticed degradation accumulating by 2027-12-31",
    "Unintended consequence: incentives shift toward short-term metrics, long-term reliability decays",
    "Incentive drift: stakeholders habituate to optimistic outputs, raising risk of silent defects"
  ],
  "mitigations": [
    "Add scheduled adversarial audits with hard pass/fail gates",
    "Track leading indicators for drift and trust inflation; alert on trend change",
    "Prefer reversible rollouts; keep rollback artifacts warm and tested"
  ],
  "block_execution": false
}