{
  "id": "fsar_fde730f2-95e2-4c69-99d3-ba33135b7f9c",
  "timestamp": "2026-01-01T00:29:03.070Z",
  "proposal": "idea_implementation: Create or update the file generated_2.sql with this complete content:\n\n-- migrations/001_create_tables.sql\nBEGIN TRANSACTION ISOLATION LEVEL READ COMMITTED; -- To avoid dirty reads and non-repeatable read issues in a multi-user environment \n\nCREATE TABLE IF NOT EXISTS users (\n    id SERIAL PRIMARY KEY,\n    email VARCHAR(255) UNIQUE NOT NULL,\n    password_hash TEXT NOT NULL,\n    ... other user fields...\n);\n\nCREATE TABLE IF NOT EXISTS courses (\n    course_id SERIAL PRIMARY KEY,\n    title VARCHAR(255) NOT NULL,\n    description TEXT NOT NULL,\n    content JSONB CHECK (content->>'type' IN ('text', 'video', 'quiz')), -- Ensure only accepted types are inserted for dynamic field flexibility. \n    ... other course fields...\n);\n\nCREATE TABLE IF NOT EXISTS enrollments (\n    user_id INT REFERENCES users(id) ON DELETE CASCADE,\n    course_id INT REFERENCES courses(course_id) ON DELETE CASCADE,\n    created_at TIMESTAMP WITH TIME ZONE DEFAULT NOW(), -- Captures the time of enrollment. \n    ... other relevant fields...\n);\n\nCREATE TABLE IF NOT EXISTS payments (\n    transaction_id SERIAL PRIMARY KEY,\n    user_id INT REFERENCES users(id) ON DELETE CASCADE,\n    course_id INT REFERENCES courses(course_id) ON DELETE SET NULL -- Optional for soft deletion of payment records. \n);\n\n-- Other necessary migrations like creating indexes go here...\n\nCOMMIT;\n\nThis is for opportunity: Online Course Creation Service\nMake sure the file is complete, working, and production-ready.",
  "severity": 6,
  "risks": [
    "Slow failure: unnoticed degradation accumulating by 2027-12-31",
    "Unintended consequence: incentives shift toward short-term metrics, long-term reliability decays",
    "Incentive drift: stakeholders habituate to optimistic outputs, raising risk of silent defects"
  ],
  "mitigations": [
    "Add scheduled adversarial audits with hard pass/fail gates",
    "Track leading indicators for drift and trust inflation; alert on trend change",
    "Prefer reversible rollouts; keep rollback artifacts warm and tested"
  ],
  "block_execution": false
}