{
  "id": "fsar_551fff37-9434-4aeb-aa8c-949579d334bc",
  "timestamp": "2026-01-01T20:11:56.643Z",
  "proposal": "idea_implementation: Create or update the file generated_5.js with this complete content:\n\n### Configuration Files ###  \nThis would primarily include Kubernetes and Helm chart configuration files, which are too extensive to cover in detail here but should be structured as YAML or JSON depending on the specifics of Railway's environment. They will define services like our AI service container with Python TensorFlow/PyTorch backend for SEO analysis processing, Docker containers for frontend and microservices components, Helm chart definitions if needed (for Kubernetes deployment), etc.\n\nThis is for opportunity: AI-Powered SEO Services\nMake sure the file is complete, working, and production-ready.",
  "severity": 6,
  "risks": [
    "Slow failure: unnoticed degradation accumulating by 2028-01-01",
    "Unintended consequence: incentives shift toward short-term metrics, long-term reliability decays",
    "Incentive drift: stakeholders habituate to optimistic outputs, raising risk of silent defects"
  ],
  "mitigations": [
    "Add scheduled adversarial audits with hard pass/fail gates",
    "Track leading indicators for drift and trust inflation; alert on trend change",
    "Prefer reversible rollouts; keep rollback artifacts warm and tested"
  ],
  "block_execution": false
}