{
  "id": "fsar_739aac2c-c685-44d4-8b65-d1d4db12f168",
  "timestamp": "2026-01-01T12:43:24.072Z",
  "proposal": "idea_implementation: Create or update the file generated_4.js with this complete content:\n\n// file: routes/api.js\nconst express = require('express');\nconst router = new express.Router();\nconst Stripe = require('stripe')(process.env.STRIPE_SECRET); // Ensure to set up your .env with the correct secret key for stripe integration\n\nrouter.get('/api/v1/system/customer-insights', async (req, res) => {\n  try {\n    const customerInsights = await Stripe().customers.list('IN_CUSTOMER_ID'); // IN_CUSTOMER_ID should be replaced with the actual ID after authenticating via OAuth token in request headers or query params as necessary for security\n    res.json(customerInsights);\n  } catch (error) {\n    res.status(500).send('Error fetching customer insights');\n 0xFF, 'A', 0x7F]; // Example character ranges to check in the font file using libfreetype2\n}\n\nThis is for opportunity: AI-Driven Customer Insights Service\nMake sure the file is complete, working, and production-ready.",
  "severity": 6,
  "risks": [
    "Slow failure: unnoticed degradation accumulating by 2028-01-01",
    "Unintended consequence: incentives shift toward short-term metrics, long-term reliability decays",
    "Incentive drift: stakeholders habituate to optimistic outputs, raising risk of silent defects"
  ],
  "mitigations": [
    "Add scheduled adversarial audits with hard pass/fail gates",
    "Track leading indicators for drift and trust inflation; alert on trend change",
    "Prefer reversible rollouts; keep rollback artifacts warm and tested"
  ],
  "block_execution": false
}