{
  "id": "fsar_13268e4b-9478-4210-adde-4a520c8385a9",
  "timestamp": "2025-12-31T23:35:29.553Z",
  "proposal": "idea_implementation: Create or update the file migrations/2023_create_customers_table.sql with this complete content:\n\nCREATE TABLE IF NOT EXISTS customers (\n    id SERIAL PRIMARY KEY,\n    name VARCHAR(100),\n    email VARCHAR(150) UNIQUE NOT NULL,\n    phone NUMERIC CHECK (phone >= 100 and phone <= 99999),\n    created_at TIMESTAMP WITH TIME ZONE DEFAULT CURRENT_TIMESTAMP\n);\n\nThis is for opportunity: AI-Driven Service Workflows\nMake sure the file is complete, working, and production-ready.",
  "severity": 6,
  "risks": [
    "Slow failure: unnoticed degradation accumulating by 2027-12-31",
    "Unintended consequence: incentives shift toward short-term metrics, long-term reliability decays",
    "Incentive drift: stakeholders habituate to optimistic outputs, raising risk of silent defects"
  ],
  "mitigations": [
    "Add scheduled adversarial audits with hard pass/fail gates",
    "Track leading indicators for drift and trust inflation; alert on trend change",
    "Prefer reversible rollouts; keep rollback artifacts warm and tested"
  ],
  "block_execution": false
}