{
  "session_id": "SESSION-DELIBERATION-V27-2026-06-09",
  "mission_id": "FACTORY-DELIBERATION-V27-0001",
  "execution_path": "reverse_bp",
  "aspects": [
    {
      "aspect_id": "A01-vocabulary-docs",
      "title": "Vocabulary v2.7 + governance docs sealed",
      "fp_ref": "docs/architecture/FOUNDER_VOCABULARY_CONSENSUS_REPORT.md",
      "blueprint_steps": [],
      "maturity_gate": "WIRED"
    },
    {
      "aspect_id": "A02-db-core",
      "title": "Neon core deliberation tables migration",
      "blueprint_steps": ["D01"],
      "maturity_gate": "PROVEN"
    },
    {
      "aspect_id": "A03-db-debrief-rep",
      "title": "Founder debrief + REP catalog migration",
      "blueprint_steps": ["D02"],
      "maturity_gate": "PROVEN"
    },
    {
      "aspect_id": "A04-config-rep",
      "title": "Deliberation config + REP catalog JSON",
      "blueprint_steps": ["D03"],
      "maturity_gate": "WIRED"
    },
    {
      "aspect_id": "A05-service-governance",
      "title": "Deliberation governance service",
      "blueprint_steps": ["D04"],
      "maturity_gate": "WIRED"
    },
    {
      "aspect_id": "A06-service-debrief",
      "title": "Founder Debrief generator service",
      "blueprint_steps": ["D05"],
      "maturity_gate": "WIRED"
    },
    {
      "aspect_id": "A07-api-production",
      "title": "Production deliberation API + runtime mount",
      "blueprint_steps": ["D06"],
      "maturity_gate": "PROVEN"
    },
    {
      "aspect_id": "A08-factory-gate",
      "title": "Factory deliberation seed + BPB intake gate + HTTP routes",
      "blueprint_steps": ["D07"],
      "maturity_gate": "WIRED"
    },
    {
      "aspect_id": "A09-builder-hook",
      "title": "Council /build deliberation seed + finalize",
      "blueprint_steps": ["D08"],
      "maturity_gate": "WIRED"
    },
    {
      "aspect_id": "A10-gate-change",
      "title": "Gate-change Position E/K + deliberation auto-persist",
      "blueprint_steps": ["D09"],
      "maturity_gate": "WIRED"
    },
    {
      "aspect_id": "A11-historian-factory",
      "title": "Factory historian consensus persist (no stub)",
      "blueprint_steps": [],
      "maturity_gate": "WIRED"
    },
    {
      "aspect_id": "A12-boot-rep",
      "title": "REP catalog boot sync",
      "blueprint_steps": ["D12"],
      "maturity_gate": "WIRED"
    },
    {
      "aspect_id": "A13-verify-smoke",
      "title": "Verify script + A→Z smoke orchestrator",
      "blueprint_steps": ["D10", "D11"],
      "maturity_gate": "WIRED"
    },
    {
      "aspect_id": "A14-mission-pack",
      "title": "Mission pack contracts (FP/BP/acceptance/SENTRY self)",
      "blueprint_steps": ["D01", "D02", "D03", "D04", "D05", "D06", "D07", "D08", "D09", "D10", "D11", "D12"],
      "maturity_gate": "WIRED"
    }
  ]
}
